wexample_wex_addon_dev_flutter-0.0.57.dist-info/METADATA
wexample_wex_addon_dev_flutter-0.0.57.dist-info/WHEEL
wexample_wex_addon_dev_flutter-0.0.57.dist-info/entry_points.txt
wexample_wex_addon_dev_flutter/__init__.py
wexample_wex_addon_dev_flutter/__pycache__/__init__.py
wexample_wex_addon_dev_flutter/config_value/__init__.py
wexample_wex_addon_dev_flutter/config_value/flutter_package_readme_config_value.py
wexample_wex_addon_dev_flutter/file/__init__.py
wexample_wex_addon_dev_flutter/file/flutter_pubspec_yaml_file.py
wexample_wex_addon_dev_flutter/flutter_addon_manager.py
wexample_wex_addon_dev_flutter/py.typed
wexample_wex_addon_dev_flutter/workdir/__init__.py
wexample_wex_addon_dev_flutter/workdir/flutter_package_workdir.py
wexample_wex_addon_dev_flutter/workdir/flutter_packages_suite_workdir.py
wexample_wex_addon_dev_flutter/workdir/flutter_workdir.py
wexample_wex_addon_dev_flutter-0.0.57.dist-info/RECORD
