Metadata-Version: 2.1
Name: wexample-wex-addon-dev-flutter
Version: 0.0.57
Summary: Python dev addon for wex
Author-Email: weeger <contact@wexample.com>
License: MIT
Classifier: Programming Language :: Python :: 3
Classifier: License :: OSI Approved :: MIT License
Classifier: Operating System :: OS Independent
Project-URL: homepage, https://github.com/wexample/python-wex-dev-python
Requires-Python: >=3.10
Requires-Dist: attrs>=23.1.0
Requires-Dist: cattrs>=23.1.0
Requires-Dist: wexample-filestate-flutter==0.0.15
Requires-Dist: wexample-wex-addon-app==0.0.55
Requires-Dist: wexample-wex-core==6.0.67
Provides-Extra: dev
Requires-Dist: pytest; extra == "dev"
Requires-Dist: pytest-cov; extra == "dev"
